ayjay/__init__.py
ayjay-0.1.2.dist-info/METADATA
ayjay-0.1.2.dist-info/WHEEL
ayjay-0.1.2.dist-info/RECORD
